{
  "position": [
    {
      "contentId": 264570,
      "contenttypeId": 12,
      "areaCode": 1,
      "sigunguCode": 1,
      "mapx": 127.02816,
      "mapy": 37.497047,
      "title": "강남",
      "firstimage": "http://tong.visitkorea.or.kr/cms/resource/08/1984608_image2_1.jpg",
      "tel": "",
      "zipcode": "06232"
    },
    {
      "contentId": 2456536,
      "contenttypeId": 12,
      "areaCode": 1,
      "sigunguCode": 1,
      "mapx": 127.059135,
      "mapy": 37.51181,
      "title": "강남 마이스 관광특구",
      "firstimage": "",
      "tel": "",
      "zipcode": "06164"
    },
    {
      "contentId": 1949905,
      "contenttypeId": 12,
      "areaCode": 1,
      "sigunguCode": 1,
      "mapx": 127.026436,
      "mapy": 37.52699,
      "title": "강남 시티투어 (트롤리버스)",
      "firstimage": "http://tong.visitkorea.or.kr/cms/resource/75/1258175_image2_1.jpg",
      "tel": "",
      "zipcode": "06001"
    },
    {
      "contentId": 2937311,
      "contenttypeId": 12,
      "areaCode": 1,
      "sigunguCode": 1,
      "mapx": 127.030945,
      "mapy": 37.515778,
      "title": "네츄럴 스파 블랑",
      "firstimage": "",
      "tel": "",
      "zipcode": "06052"
    },
    {
      "contentId": 1603149,
      "contenttypeId": 12,
      "areaCode": 1,
      "sigunguCode": 1,
      "mapx": 127.052605,
      "mapy": 37.47173,
      "title": "능인선원",
      "firstimage": "http://tong.visitkorea.or.kr/cms/resource/72/1567772_image2_1.jpg",
      "tel": "",
      "zipcode": "06357"
    },
    {
      "contentId": 1602451,
      "contenttypeId": 12,
      "areaCode": 1,
      "sigunguCode": 1,
      "mapx": 127.07509,
      "mapy": 37.477585,
      "title": "대모산공원",
      "firstimage": "http://tong.visitkorea.or.kr/cms/resource/51/1567751_image2_1.jpg",
      "tel": "",
      "zipcode": "06359"
    },
    {
      "contentId": 2733970,
      "contenttypeId": 12,
      "areaCode": 1,
      "sigunguCode": 1,
      "mapx": 127.06356,
      "mapy": 37.501633,
      "title": "대치유수지체육공원",
      "firstimage": "http://tong.visitkorea.or.kr/cms/resource/90/2779090_image2_1.jpg",
      "tel": "",
      "zipcode": "06190"
    },
    {
      "contentId": 126486,
      "contenttypeId": 12,
      "areaCode": 1,
      "sigunguCode": 1,
      "mapx": 127.03381,
      "mapy": 37.52146,
      "title": "도산공원",
      "firstimage": "http://tong.visitkorea.or.kr/cms/resource/60/2678560_image2_1.jpg",
      "tel": "",
      "zipcode": "06020"
    },
    {
      "contentId": 2720441,
      "contenttypeId": 12,
      "areaCode": 1,
      "sigunguCode": 1,
      "mapx": 127.027336,
      "mapy": 37.521942,
      "title": "립바이 메이크업 스튜디오",
      "firstimage": "",
      "tel": "",
      "zipcode": "06032"
    },
    {
      "contentId": 2752525,
      "contenttypeId": 12,
      "areaCode": 1,
      "sigunguCode": 1,
      "mapx": 127.08014,
      "mapy": 37.495937,
      "title": "마루공원",
      "firstimage": "",
      "tel": "",
      "zipcode": "06334"
    },
    {
      "contentId": 2946528,
      "contenttypeId": 12,
      "areaCode": 1,
      "sigunguCode": 1,
      "mapx": 127.03396,
      "mapy": 37.516743,
      "title": "면역공방 블랙점",
      "firstimage": "http://tong.visitkorea.or.kr/cms/resource/19/2947019_image2_1.jpg",
      "tel": "",
      "zipcode": "06053"
    },
    {
      "contentId": 126504,
      "contenttypeId": 12,
      "areaCode": 1,
      "sigunguCode": 1,
      "mapx": 127.05775,
      "mapy": 37.515877,
      "title": "봉은사(서울)",
      "firstimage": "http://tong.visitkorea.or.kr/cms/resource/37/2652137_image2_1.jpg",
      "tel": "",
      "zipcode": "06087"
    },
    {
      "contentId": 2782188,
      "contenttypeId": 12,
      "areaCode": 1,
      "sigunguCode": 1,
      "mapx": 127.0403,
      "mapy": 37.494926,
      "title": "불교총지종",
      "firstimage": "http://tong.visitkorea.or.kr/cms/resource/18/2782218_image2_1.jpg",
      "tel": "",
      "zipcode": "06227"
    },
    {
      "contentId": 1603100,
      "contenttypeId": 12,
      "areaCode": 1,
      "sigunguCode": 1,
      "mapx": 127.07508,
      "mapy": 37.4776,
      "title": "불국사",
      "firstimage": "http://tong.visitkorea.or.kr/cms/resource/58/1567758_image2_1.jpg",
      "tel": "",
      "zipcode": "06359"
    },
    {
      "contentId": 2559938,
      "contenttypeId": 12,
      "areaCode": 1,
      "sigunguCode": 1,
      "mapx": 127.05944,
      "mapy": 37.511715,
      "title": "브이알존 엑스 코엑스 직영점",
      "firstimage": "http://tong.visitkorea.or.kr/cms/resource/26/2559926_image2_1.jpg",
      "tel": "",
      "zipcode": "06164"
    },
    {
      "contentId": 126525,
      "contenttypeId": 12,
      "areaCode": 1,
      "sigunguCode": 1,
      "mapx": 127.04718,
      "mapy": 37.50742,
      "title": "서울 선릉(성종과 정현왕후)과 정릉(중종) [유네스코 세계문화유산]",
      "firstimage": "",
      "tel": "",
      "zipcode": "06153"
    },
    {
      "contentId": 2660725,
      "contenttypeId": 12,
      "areaCode": 1,
      "sigunguCode": 1,
      "mapx": 127.0355,
      "mapy": 37.52361,
      "title": "설화수 플래그십 스토어",
      "firstimage": "",
      "tel": "",
      "zipcode": "06021"
    },
    {
      "contentId": 2646372,
      "contenttypeId": 12,
      "areaCode": 1,
      "sigunguCode": 1,
      "mapx": 127.03313,
      "mapy": 37.508297,
      "title": "스파 도향",
      "firstimage": "http://tong.visitkorea.or.kr/cms/resource/67/2646367_image2_1.bmp",
      "tel": "",
      "zipcode": "06122"
    },
    {
      "contentId": 2946400,
      "contenttypeId": 12,
      "areaCode": 1,
      "sigunguCode": 1,
      "mapx": 127.0377,
      "mapy": 37.52543,
      "title": "신꼼꼼",
      "firstimage": "http://tong.visitkorea.or.kr/cms/resource/71/2947671_image2_1.jpg",
      "tel": "",
      "zipcode": "06019"
    },
    {
      "contentId": 2752552,
      "contenttypeId": 12,
      "areaCode": 1,
      "sigunguCode": 1,
      "mapx": 127.02128,
      "mapy": 37.526844,
      "title": "신사공원",
      "firstimage": "",
      "tel": "",
      "zipcode": "06000"
    },
    {
      "contentId": 987720,
      "contenttypeId": 12,
      "areaCode": 1,
      "sigunguCode": 1,
      "mapx": 127.02275,
      "mapy": 37.521534,
      "title": "신사동 가로수길",
      "firstimage": "http://tong.visitkorea.or.kr/cms/resource/42/2658442_image2_1.jpg",
      "tel": "",
      "zipcode": "06028"
    },
    {
      "contentId": 126823,
      "contenttypeId": 12,
      "areaCode": 1,
      "sigunguCode": 1,
      "mapx": 127.038895,
      "mapy": 37.52688,
      "title": "압구정 로데오거리",
      "firstimage": "http://tong.visitkorea.or.kr/cms/resource/70/2024970_image2_1.jpg",
      "tel": "",
      "zipcode": "06017"
    },
    {
      "contentId": 2946231,
      "contenttypeId": 12,
      "areaCode": 1,
      "sigunguCode": 1,
      "mapx": 127.042694,
      "mapy": 37.5243,
      "title": "에이바이봄",
      "firstimage": "http://tong.visitkorea.or.kr/cms/resource/87/2947687_image2_1.jpg",
      "tel": "",
      "zipcode": "06016"
    },
    {
      "contentId": 2592885,
      "contenttypeId": 12,
      "areaCode": 1,
      "sigunguCode": 1,
      "mapx": 127.02322,
      "mapy": 37.520935,
      "title": "엘크레",
      "firstimage": "http://tong.visitkorea.or.kr/cms/resource/76/2592876_image2_1.bmp",
      "tel": "",
      "zipcode": "06033"
    },
    {
      "contentId": 2752545,
      "contenttypeId": 12,
      "areaCode": 1,
      "sigunguCode": 1,
      "mapx": 127.0363,
      "mapy": 37.497654,
      "title": "역삼개나리공원",
      "firstimage": "",
      "tel": "",
      "zipcode": "06237"
    },
    {
      "contentId": 2733864,
      "contenttypeId": 12,
      "areaCode": 1,
      "sigunguCode": 1,
      "mapx": 127.0418,
      "mapy": 37.500546,
      "title": "역삼동성당",
      "firstimage": "http://tong.visitkorea.or.kr/cms/resource/67/2779567_image2_1.jpg",
      "tel": "",
      "zipcode": "06222"
    },
    {
      "contentId": 2754732,
      "contenttypeId": 12,
      "areaCode": 1,
      "sigunguCode": 1,
      "mapx": 127.106285,
      "mapy": 37.473076,
      "title": "율현공원",
      "firstimage": "",
      "tel": "",
      "zipcode": "06377"
    },
    {
      "contentId": 2751890,
      "contenttypeId": 12,
      "areaCode": 1,
      "sigunguCode": 1,
      "mapx": 127.10048,
      "mapy": 37.468113,
      "title": "은곡마을공원",
      "firstimage": "",
      "tel": "",
      "zipcode": ""
    },
    {
      "contentId": 2713582,
      "contenttypeId": 12,
      "areaCode": 1,
      "sigunguCode": 1,
      "mapx": 127.02681,
      "mapy": 37.50064,
      "title": "일상비일상의틈",
      "firstimage": "http://tong.visitkorea.or.kr/cms/resource/82/2713482_image2_1.jpg",
      "tel": "",
      "zipcode": "06129"
    },
    {
      "contentId": 2773291,
      "contenttypeId": 12,
      "areaCode": 1,
      "sigunguCode": 1,
      "mapx": 127.08453,
      "mapy": 37.491463,
      "title": "일원에코파크",
      "firstimage": "http://tong.visitkorea.or.kr/cms/resource/92/2778992_image2_1.jpg",
      "tel": "",
      "zipcode": "06343"
    },
    {
      "contentId": 2759613,
      "contenttypeId": 12,
      "areaCode": 1,
      "sigunguCode": 1,
      "mapx": 127.08084,
      "mapy": 37.48072,
      "title": "일원장미공원",
      "firstimage": "",
      "tel": "",
      "zipcode": "06359"
    },
    {
      "contentId": 753954,
      "contenttypeId": 12,
      "areaCode": 1,
      "sigunguCode": 1,
      "mapx": 127.09303,
      "mapy": 37.486923,
      "title": "전주이씨광평대군파묘역",
      "firstimage": "http://tong.visitkorea.or.kr/cms/resource/09/755409_image2_1.jpg",
      "tel": "",
      "zipcode": "06353"
    },
    {
      "contentId": 127269,
      "contenttypeId": 12,
      "areaCode": 1,
      "sigunguCode": 1,
      "mapx": 127.052666,
      "mapy": 37.521156,
      "title": "청담공원",
      "firstimage": "http://tong.visitkorea.or.kr/cms/resource/00/204200_image2_1.jpg",
      "tel": "",
      "zipcode": "06073"
    },
    {
      "contentId": 1310950,
      "contenttypeId": 12,
      "areaCode": 1,
      "sigunguCode": 1,
      "mapx": 127.04576,
      "mapy": 37.525906,
      "title": "청담패션거리",
      "firstimage": "http://tong.visitkorea.or.kr/cms/resource/82/2728682_image2_1.jpg",
      "tel": "",
      "zipcode": "06015"
    },
    {
      "contentId": 2759626,
      "contenttypeId": 12,
      "areaCode": 1,
      "sigunguCode": 1,
      "mapx": 127.05944,
      "mapy": 37.511715,
      "title": "코엑스동측광장",
      "firstimage": "",
      "tel": "",
      "zipcode": "06164"
    },
    {
      "contentId": 814181,
      "contenttypeId": 12,
      "areaCode": 1,
      "sigunguCode": 1,
      "mapx": 127.103615,
      "mapy": 37.49313,
      "title": "탄천",
      "firstimage": "http://tong.visitkorea.or.kr/cms/resource/81/1837981_image2_1.jpg",
      "tel": "",
      "zipcode": "135-210,1"
    },
    {
      "contentId": 2754735,
      "contenttypeId": 12,
      "areaCode": 1,
      "sigunguCode": 1,
      "mapx": 127.02372,
      "mapy": 37.51561,
      "title": "학동공원",
      "firstimage": "",
      "tel": "",
      "zipcode": ""
    },
    {
      "contentId": 2754738,
      "contenttypeId": 12,
      "areaCode": 1,
      "sigunguCode": 1,
      "mapx": 127.07881,
      "mapy": 37.481255,
      "title": "한솔공원",
      "firstimage": "",
      "tel": "",
      "zipcode": "06359"
    },
    {
      "contentId": 2946112,
      "contenttypeId": 12,
      "areaCode": 1,
      "sigunguCode": 1,
      "mapx": 127.03796,
      "mapy": 37.526157,
      "title": "향기억",
      "firstimage": "http://tong.visitkorea.or.kr/cms/resource/98/2947498_image2_1.jpg",
      "tel": "",
      "zipcode": "06018"
    },
    {
      "contentId": 2614315,
      "contenttypeId": 12,
      "areaCode": 1,
      "sigunguCode": 1,
      "mapx": 127.03303,
      "mapy": 37.52177,
      "title": "AHC스파",
      "firstimage": "http://tong.visitkorea.or.kr/cms/resource/05/2614305_image2_1.bmp",
      "tel": "",
      "zipcode": "06026"
    },
    {
      "contentId": 2660731,
      "contenttypeId": 12,
      "areaCode": 1,
      "sigunguCode": 1,
      "mapx": 127.065346,
      "mapy": 37.506638,
      "title": "SPA 1899 동인비",
      "firstimage": "",
      "tel": "",
      "zipcode": "06176"
    },
    {
      "contentId": 2715601,
      "contenttypeId": 12,
      "areaCode": 6,
      "sigunguCode": 1,
      "mapx": 128.81694,
      "mapy": 35.022964,
      "title": "가덕도",
      "firstimage": "http://tong.visitkorea.or.kr/cms/resource/61/2716261_image2_1.jpg",
      "tel": "",
      "zipcode": ""
    },
    {
      "contentId": 129156,
      "contenttypeId": 12,
      "areaCode": 6,
      "sigunguCode": 1,
      "mapx": 128.82959,
      "mapy": 35.00065,
      "title": "가덕도 등대",
      "firstimage": "http://tong.visitkorea.or.kr/cms/resource/88/1982388_image2_1.jpg",
      "tel": "",
      "zipcode": "46771"
    },
    {
      "contentId": 2726843,
      "contenttypeId": 12,
      "areaCode": 6,
      "sigunguCode": 1,
      "mapx": 128.82167,
      "mapy": 35.031754,
      "title": "가덕도 연대봉",
      "firstimage": "",
      "tel": "",
      "zipcode": ""
    },
    {
      "contentId": 2789460,
      "contenttypeId": 12,
      "areaCode": 6,
      "sigunguCode": 1,
      "mapx": 128.82747,
      "mapy": 35.01331,
      "title": "가덕도대항인공동굴",
      "firstimage": "http://tong.visitkorea.or.kr/cms/resource/67/2800367_image2_1.jpg",
      "tel": "",
      "zipcode": "46771"
    },
    {
      "contentId": 2782772,
      "contenttypeId": 12,
      "areaCode": 6,
      "sigunguCode": 1,
      "mapx": 128.80963,
      "mapy": 35.02306,
      "title": "가덕해양파크휴게소",
      "firstimage": "http://tong.visitkorea.or.kr/cms/resource/60/2793060_image2_1.jpg",
      "tel": "",
      "zipcode": "46770"
    },
    {
      "contentId": 2867934,
      "contenttypeId": 12,
      "areaCode": 6,
      "sigunguCode": 1,
      "mapx": 128.886,
      "mapy": 35.154316,
      "title": "녹산고향동산",
      "firstimage": "http://tong.visitkorea.or.kr/cms/resource/14/2867914_image2_1.JPG",
      "tel": "",
      "zipcode": "46727"
    },
    {
      "contentId": 2487925,
      "contenttypeId": 12,
      "areaCode": 6,
      "sigunguCode": 1,
      "mapx": 128.98457,
      "mapy": 35.209873,
      "title": "대저생태공원",
      "firstimage": "",
      "tel": "",
      "zipcode": "46703"
    },
    {
      "contentId": 2748838,
      "contenttypeId": 12,
      "areaCode": 6,
      "sigunguCode": 1,
      "mapx": 128.99242,
      "mapy": 35.230095,
      "title": "대저수문 생태공원",
      "firstimage": "",
      "tel": "",
      "zipcode": ""
    },
    {
      "contentId": 128564,
      "contenttypeId": 12,
      "areaCode": 6,
      "sigunguCode": 1,
      "mapx": 128.8277,
      "mapy": 35.011723,
      "title": "대항 어촌체험 휴양마을",
      "firstimage": "http://tong.visitkorea.or.kr/cms/resource/26/2607126_image2_1.bmp",
      "tel": "",
      "zipcode": "46771"
    },
    {
      "contentId": 2785960,
      "contenttypeId": 12,
      "areaCode": 6,
      "sigunguCode": 1,
      "mapx": 128.826,
      "mapy": 35.01233,
      "title": "대항선착장",
      "firstimage": "http://tong.visitkorea.or.kr/cms/resource/06/2800406_image2_1.jpg",
      "tel": "",
      "zipcode": "46771"
    },
    {
      "contentId": 2744553,
      "contenttypeId": 12,
      "areaCode": 6,
      "sigunguCode": 1,
      "mapx": 128.82512,
      "mapy": 35.01716,
      "title": "대항전망대",
      "firstimage": "http://tong.visitkorea.or.kr/cms/resource/91/2744891_image2_1.jpg",
      "tel": "",
      "zipcode": "46771"
    },
    {
      "contentId": 2791383,
      "contenttypeId": 12,
      "areaCode": 6,
      "sigunguCode": 1,
      "mapx": 128.92206,
      "mapy": 35.13641,
      "title": "델타루 (에코델타시티 전망대)",
      "firstimage": "http://tong.visitkorea.or.kr/cms/resource/87/2791387_image2_1.JPG",
      "tel": "",
      "zipcode": ""
    },
    {
      "contentId": 250424,
      "contenttypeId": 12,
      "areaCode": 6,
      "sigunguCode": 1,
      "mapx": 128.82092,
      "mapy": 35.096725,
      "title": "망산도·유주암·유주비각",
      "firstimage": "",
      "tel": "",
      "zipcode": "51610"
    },
    {
      "contentId": 2487927,
      "contenttypeId": 12,
      "areaCode": 6,
      "sigunguCode": 1,
      "mapx": 128.95493,
      "mapy": 35.152348,
      "title": "맥도생태공원",
      "firstimage": "http://tong.visitkorea.or.kr/cms/resource/23/2488023_image2_1.JPG",
      "tel": "",
      "zipcode": "46723"
    },
    {
      "contentId": 2789334,
      "contenttypeId": 12,
      "areaCode": 6,
      "sigunguCode": 1,
      "mapx": 128.84325,
      "mapy": 35.088146,
      "title": "보람공원",
      "firstimage": "",
      "tel": "",
      "zipcode": "46757"
    },
    {
      "contentId": 2789340,
      "contenttypeId": 12,
      "areaCode": 6,
      "sigunguCode": 1,
      "mapx": 128.90666,
      "mapy": 35.087032,
      "title": "명지동근린공원",
      "firstimage": "",
      "tel": "",
      "zipcode": "46763"
    },
    {
      "contentId": 2732397,
      "contenttypeId": 12,
      "areaCode": 6,
      "sigunguCode": 1,
      "mapx": 128.97978,
      "mapy": 35.209393,
      "title": "물빛색스튜디오",
      "firstimage": "",
      "tel": "",
      "zipcode": "46703"
    },
    {
      "contentId": 2788828,
      "contenttypeId": 12,
      "areaCode": 6,
      "sigunguCode": 1,
      "mapx": 128.87077,
      "mapy": 35.081913,
      "title": "신호공원",
      "firstimage": "",
      "tel": "",
      "zipcode": ""
    },
    {
      "contentId": 2788831,
      "contenttypeId": 12,
      "areaCode": 6,
      "sigunguCode": 1,
      "mapx": 128.83295,
      "mapy": 35.030598,
      "title": "연태봉",
      "firstimage": "",
      "tel": "",
      "zipcode": ""
    },
    {
      "contentId": 2605602,
      "contenttypeId": 12,
      "areaCode": 6,
      "sigunguCode": 1,
      "mapx": 128.8252,
      "mapy": 35.00564,
      "title": "외양포 포진지",
      "firstimage": "http://tong.visitkorea.or.kr/cms/resource/77/2603377_image2_1.jpg",
      "tel": "",
      "zipcode": "46771"
    },
    {
      "contentId": 2788826,
      "contenttypeId": 12,
      "areaCode": 6,
      "sigunguCode": 1,
      "mapx": 128.83295,
      "mapy": 35.030598,
      "title": "외양포항",
      "firstimage": "",
      "tel": "",
      "zipcode": ""
    },
    {
      "contentId": 2788827,
      "contenttypeId": 12,
      "areaCode": 6,
      "sigunguCode": 1,
      "mapx": 128.92703,
      "mapy": 35.10166,
      "title": "울림공원",
      "firstimage": "",
      "tel": "",
      "zipcode": ""
    },
    {
      "contentId": 2744560,
      "contenttypeId": 12,
      "areaCode": 6,
      "sigunguCode": 1,
      "mapx": 128.8149,
      "mapy": 35.028217,
      "title": "천성항 방파제등대",
      "firstimage": "http://tong.visitkorea.or.kr/cms/resource/03/2744903_image2_1.jpg",
      "tel": "",
      "zipcode": "46770"
    },
    {
      "contentId": 482123,
      "contenttypeId": 12,
      "areaCode": 6,
      "sigunguCode": 1,
      "mapx": 128.91908,
      "mapy": 35.11776,
      "title": "청량사(부산)",
      "firstimage": "http://tong.visitkorea.or.kr/cms/resource/59/1152559_image2_1.jpg",
      "tel": "",
      "zipcode": "46717"
    },
    {
      "contentId": 2791357,
      "contenttypeId": 12,
      "areaCode": 6,
      "sigunguCode": 1,
      "mapx": 128.87917,
      "mapy": 35.105656,
      "title": "화전공원",
      "firstimage": "http://tong.visitkorea.or.kr/cms/resource/70/2791370_image2_1.jpg",
      "tel": "",
      "zipcode": "46738"
    }
  ]
}
